cspeech_lib.cpython-38-darwin.so
cspeech_lib-0.0.6.dist-info/METADATA
cspeech_lib-0.0.6.dist-info/WHEEL
cspeech_lib-0.0.6.dist-info/top_level.txt
cspeech_lib-0.0.6.dist-info/RECORD
