Metadata-Version: 2.1
Name: cspeech-lib
Version: 0.0.6
Summary: Fast C++ modules for SpeechAPI project.
Home-page: https://github.com/PiotrDabkowski/SpeechAPI
Author: Piotr Dabkowski
Author-email: UNKNOWN
License: UNKNOWN
Platform: UNKNOWN
